{"_type":"export","__export_format":4,"__export_date":"2022-05-13T12:13:30.775Z","__export_source":"insomnia.desktop.app:v2022.3.0","resources":[{"_id":"req_f572702c95294d5788cba56618cf7055","parentId":"fld_5fe74f615a7640918e9d1be25760f150","modified":1652361594805,"created":1648202726805,"url":"{{ _.URL }}/api/workouts","name":"POST /api/workouts","description":"","method":"POST","body":{"mimeType":"application/json","text":"\n{\n\t\"name\": \"Chestwe exercises\",\n\t\"exerciseIds\": [\n\t\t\"623d938abfa078523611e122\"\n\t]\n}"},"parameters":[],"headers":[{"name":"Content-Type","value":"application/json","id":"pair_6257013847d3437db8aad41c78826168"}],"authentication":{"type":"bearer","token":"{{ _.TOKEN }}"},"metaSortKey":-1648201365666,"isPrivate":false,"settingStoreCookies":true,"settingSendCookies":true,"settingDisableRenderRequestBody":false,"settingEncodeUrl":true,"settingRebuildPath":true,"settingFollowRedirects":"global","_type":"request"},{"_id":"fld_5fe74f615a7640918e9d1be25760f150","parentId":"wrk_eee28770aef8475d9353d62399da17c3","modified":1648201365716,"created":1648201365716,"name":"Workouts","description":"","environment":{},"environmentPropertyOrder":null,"metaSortKey":-1648201365716,"_type":"request_group"},{"_id":"wrk_eee28770aef8475d9353d62399da17c3","parentId":null,"modified":1647179707804,"created":1647179707804,"name":"New Document","description":"","scope":"design","_type":"workspace"},{"_id":"req_c31931356e034d5499f9dea0ba1f9c7c","parentId":"fld_5fe74f615a7640918e9d1be25760f150","modified":1652361596014,"created":1648203300623,"url":"{{ _.URL }}/api/workouts/6261277f46d61bbb119cffd2","name":"GET/api/workouts/:id","description":"","method":"GET","body":{},"parameters":[],"headers":[],"authentication":{"type":"bearer","token":"{{ _.TOKEN }}"},"metaSortKey":-1647858829961,"isPrivate":false,"settingStoreCookies":true,"settingSendCookies":true,"settingDisableRenderRequestBody":false,"settingEncodeUrl":true,"settingRebuildPath":true,"settingFollowRedirects":"global","_type":"request"},{"_id":"req_231d49f2b67e4a4090693edf5717afb1","parentId":"fld_5fe74f615a7640918e9d1be25760f150","modified":1651738776160,"created":1648549720641,"url":"{{ _.URL }}/api/workouts/log","name":"POST /api/workouts/log","description":"","method":"POST","body":{"mimeType":"application/json","text":"{\n\t\"workoutId\": \"62690c6597e1abd1e074045d\"\n}"},"parameters":[],"headers":[{"name":"Content-Type","value":"application/json","id":"pair_6257013847d3437db8aad41c78826168"}],"authentication":{"type":"bearer","token":"{{ _.TOKEN }}"},"metaSortKey":-1648030097813.5,"isPrivate":false,"settingStoreCookies":true,"settingSendCookies":true,"settingDisableRenderRequestBody":false,"settingEncodeUrl":true,"settingRebuildPath":true,"settingFollowRedirects":"global","_type":"request"},{"_id":"req_b25ffda72bcc46b98c4caeec5f9ab82a","parentId":"fld_5fe74f615a7640918e9d1be25760f150","modified":1652361994235,"created":1648553179454,"url":"{{ _.URL }}/api/workouts","name":"PUT /api/workouts","description":"","method":"PUT","body":{"mimeType":"application/json","text":"{\n\t\"name\": \"Shoulders exercises\",\n\t\"exerciseIds\": [\n\t\t\"623d938abfa078523611e122\"\n\t],\n\t\"workoutId\": \"623d94cabfa078523611e128\"\n}"},"parameters":[],"headers":[{"name":"Content-Type","value":"application/json","id":"pair_6257013847d3437db8aad41c78826168"}],"authentication":{"type":"bearer","token":"{{ _.TOKEN }}"},"metaSortKey":-1648115731739.75,"isPrivate":false,"settingStoreCookies":true,"settingSendCookies":true,"settingDisableRenderRequestBody":false,"settingEncodeUrl":true,"settingRebuildPath":true,"settingFollowRedirects":"global","_type":"request"},{"_id":"req_90008d1fd0ed4840b13da118e0b9210c","parentId":"fld_5fe74f615a7640918e9d1be25760f150","modified":1652361989159,"created":1650966847994,"url":"{{ _.URL }}/api/workouts","name":"GET/api/workouts","description":"","method":"GET","body":{},"parameters":[],"headers":[],"authentication":{"type":"bearer","token":"{{ _.TOKEN }}"},"metaSortKey":-1647687562108.5,"isPrivate":false,"settingStoreCookies":true,"settingSendCookies":true,"settingDisableRenderRequestBody":false,"settingEncodeUrl":true,"settingRebuildPath":true,"settingFollowRedirects":"global","_type":"request"},{"_id":"req_b9d0fafad6a048d39510cf4197b5bc72","parentId":"fld_1c3b989298ba4ac9bcf9bca10eeec67c","modified":1652433827022,"created":1647179707873,"url":"{{ _.URL }}/api/users/login","name":"POST /api/users/login","description":"","method":"POST","body":{"mimeType":"application/json","text":"{\n\t\"email\": \"d.gnatishen@gmail.com\",\n\t\"password\": \"admin\"\n}"},"parameters":[],"headers":[{"name":"Content-Type","value":"application/json","id":"pair_8254bd1f4ddf4ea2b189781a95560aa4"}],"authentication":{},"metaSortKey":-1647516294256,"isPrivate":false,"settingStoreCookies":true,"settingSendCookies":true,"settingDisableRenderRequestBody":false,"settingEncodeUrl":true,"settingRebuildPath":true,"settingFollowRedirects":"global","_type":"request"},{"_id":"fld_1c3b989298ba4ac9bcf9bca10eeec67c","parentId":"wrk_eee28770aef8475d9353d62399da17c3","modified":1648201374882,"created":1648201374882,"name":"Users","description":"","environment":{},"environmentPropertyOrder":null,"metaSortKey":-1648201374882,"_type":"request_group"},{"_id":"req_855135713c874064adc0d8a30d83ad37","parentId":"fld_1c3b989298ba4ac9bcf9bca10eeec67c","modified":1652433822388,"created":1647184867233,"url":"{{ _.URL }}/api/users/profile","name":"GET /api/users/profile","description":"Get Profile user. Only private","method":"GET","body":{},"parameters":[],"headers":[],"authentication":{"type":"bearer","token":"{{ _.TOKEN }}"},"metaSortKey":-1647516294231,"isPrivate":false,"settingStoreCookies":true,"settingSendCookies":true,"settingDisableRenderRequestBody":false,"settingEncodeUrl":true,"settingRebuildPath":true,"settingFollowRedirects":"global","_type":"request"},{"_id":"req_5cb36037818f4204b2ba792df645677c","parentId":"fld_1c3b989298ba4ac9bcf9bca10eeec67c","modified":1652433821196,"created":1647516294206,"url":"{{ _.URL }}/api/users","name":"POST/api/users","description":"","method":"POST","body":{"mimeType":"application/json","text":"{\n\t\"email\": \"test@3test.ru\",\n\t\"password\": \"12345\"\n}"},"parameters":[],"headers":[{"name":"Content-Type","value":"application/json","id":"pair_8dc67533127946c0810acf4c1083705d"}],"authentication":{},"metaSortKey":-1647516294206,"isPrivate":false,"settingStoreCookies":true,"settingSendCookies":true,"settingDisableRenderRequestBody":false,"settingEncodeUrl":true,"settingRebuildPath":true,"settingFollowRedirects":"global","_type":"request"},{"_id":"req_93337a9a59ec449e8f9d8e8deeb76674","parentId":"fld_88b6341d9bd94af8bdf58bf21a4e6263","modified":1652359881279,"created":1648202479886,"url":"{{ _.URL }}/api/exercises","name":"POST /api/exercises","description":"","method":"POST","body":{"mimeType":"application/json","text":"{\n\t\"name\": \"Push-ups\",\n\t\"times\": 3,\n\t\"imageName\": \"biceps\"\n}"},"parameters":[],"headers":[{"name":"Content-Type","value":"application/json","id":"pair_6257013847d3437db8aad41c78826168"}],"authentication":{"type":"bearer","token":"{{ _.TOKEN }}"},"metaSortKey":-1648202479886,"isPrivate":false,"settingStoreCookies":true,"settingSendCookies":true,"settingDisableRenderRequestBody":false,"settingEncodeUrl":true,"settingRebuildPath":true,"settingFollowRedirects":"global","_type":"request"},{"_id":"fld_88b6341d9bd94af8bdf58bf21a4e6263","parentId":"wrk_eee28770aef8475d9353d62399da17c3","modified":1648201403438,"created":1648201403438,"name":"Exercises","description":"","environment":{},"environmentPropertyOrder":null,"metaSortKey":-1648201403438,"_type":"request_group"},{"_id":"req_e59a38d2a775440693d1ee8942652cb2","parentId":"fld_88b6341d9bd94af8bdf58bf21a4e6263","modified":1652349891374,"created":1648553419355,"url":"{{ _.URL }}/api/exercises","name":"PUT/api/exercises","description":"","method":"PUT","body":{"mimeType":"application/json","text":"{\n\t\"name\": \"Pull-ups\",\n\t\"times\": 4,\n\t\"imageName\": \"biceps\",\n\t\"exerciseId\": \"623d938abfa078523611e122\"\n}"},"parameters":[],"headers":[{"name":"Content-Type","value":"application/json","id":"pair_6257013847d3437db8aad41c78826168"}],"authentication":{"type":"bearer","token":"{{ _.TOKEN }}"},"metaSortKey":-1648202131692.25,"isPrivate":false,"settingStoreCookies":true,"settingSendCookies":true,"settingDisableRenderRequestBody":false,"settingEncodeUrl":true,"settingRebuildPath":true,"settingFollowRedirects":"global","_type":"request"},{"_id":"req_15432247e3124c67ad78c4cdb1bf8c65","parentId":"fld_88b6341d9bd94af8bdf58bf21a4e6263","modified":1652437002809,"created":1648807464458,"url":"{{ _.URL }}/api/exercises","name":"GET /api/exercises","description":"","method":"GET","body":{"mimeType":"application/json","text":""},"parameters":[],"headers":[{"name":"Content-Type","value":"application/json","id":"pair_a0f93600cdb64708856b64cf81698c73"}],"authentication":{"type":"bearer","token":"{{ _.TOKEN }}"},"metaSortKey":-1648807464458,"isPrivate":false,"settingStoreCookies":true,"settingSendCookies":true,"settingDisableRenderRequestBody":false,"settingEncodeUrl":true,"settingRebuildPath":true,"settingFollowRedirects":"global","_type":"request"},{"_id":"req_b817537ffc954dbebcb5c157462a9847","parentId":"fld_88b6341d9bd94af8bdf58bf21a4e6263","modified":1652437037407,"created":1652349641552,"url":"{{ _.URL }}/api/exercises","name":"DELETE/api/exercises","description":"","method":"DELETE","body":{"mimeType":"","text":"{\n\t\"exerciseId\": \"6242ef54e296cda88784b2a9\"\n}"},"parameters":[],"headers":[{"name":"Content-Type","value":"application/json","id":"pair_6257013847d3437db8aad41c78826168"}],"authentication":{"type":"bearer","token":"{{ _.TOKEN }}"},"metaSortKey":-1648201957595.375,"isPrivate":false,"settingStoreCookies":true,"settingSendCookies":true,"settingDisableRenderRequestBody":false,"settingEncodeUrl":true,"settingRebuildPath":true,"settingFollowRedirects":"global","_type":"request"},{"_id":"req_b7ab027be67d4551a4b9847ecfb8148d","parentId":"fld_cdf95cbbb20c4c64ac41a1dfaf5d2fde","modified":1652433752859,"created":1648209632512,"url":"{{ _.URL }}/api/exercises/log","name":"POST /api/exercises/log","description":"","method":"POST","body":{"mimeType":"application/json","text":"{\n\t\"exerciseId\": \"623d938abfa078523611e122\",\n\t\"times\": 3\n}"},"parameters":[],"headers":[{"name":"Content-Type","value":"application/json","id":"pair_6257013847d3437db8aad41c78826168"}],"authentication":{"type":"bearer","token":"{{ _.TOKEN }}"},"metaSortKey":-1648201783398.5,"isPrivate":false,"settingStoreCookies":true,"settingSendCookies":true,"settingDisableRenderRequestBody":false,"settingEncodeUrl":true,"settingRebuildPath":true,"settingFollowRedirects":"global","_type":"request"},{"_id":"fld_cdf95cbbb20c4c64ac41a1dfaf5d2fde","parentId":"fld_88b6341d9bd94af8bdf58bf21a4e6263","modified":1648553379131,"created":1648553379131,"name":"log","description":"","environment":{},"environmentPropertyOrder":null,"metaSortKey":-1648553379131,"_type":"request_group"},{"_id":"req_6ce399b5cb4949b18cdb1f5373a83000","parentId":"fld_cdf95cbbb20c4c64ac41a1dfaf5d2fde","modified":1652433747975,"created":1648215146841,"url":"{{ _.URL }}/api/exercises/log/62738650af8effd3bedc2634","name":"GET/api/exercises/log/:id","description":"","method":"GET","body":{},"parameters":[],"headers":[],"authentication":{"type":"bearer","token":"{{ _.TOKEN }}"},"metaSortKey":-1648201783448.5,"isPrivate":false,"settingStoreCookies":true,"settingSendCookies":true,"settingDisableRenderRequestBody":false,"settingEncodeUrl":true,"settingRebuildPath":true,"settingFollowRedirects":"global","_type":"request"},{"_id":"req_1094151b172f4fc899def060e6022364","parentId":"fld_cdf95cbbb20c4c64ac41a1dfaf5d2fde","modified":1652437002474,"created":1648541681847,"url":"{{ _.URL }}/api/exercises/log","name":"PUT /api/exercises/log","description":"","method":"PUT","body":{"mimeType":"application/json","text":"{\n\t\"logId\": \"627398eb4347e0977cd9b4fc\",\n\t\"timeIndex\": 1,\n\t\"key\": \"repeat\",\n\t\"value\": 5\n}"},"parameters":[],"headers":[{"name":"Content-Type","value":"application/json","id":"pair_6257013847d3437db8aad41c78826168"}],"authentication":{"type":"bearer","token":"{{ _.TOKEN }}"},"metaSortKey":-1648201783498.5,"isPrivate":false,"settingStoreCookies":true,"settingSendCookies":true,"settingDisableRenderRequestBody":false,"settingEncodeUrl":true,"settingRebuildPath":true,"settingFollowRedirects":"global","_type":"request"},{"_id":"req_4ec696be9ecc4135943c404d1b69a5a8","parentId":"fld_cdf95cbbb20c4c64ac41a1dfaf5d2fde","modified":1651736969193,"created":1648545147038,"url":"{{ _.URL }}/api/exercises/log/completed","name":"PUT /api/exercises/log/completed","description":"","method":"PUT","body":{"mimeType":"application/json","text":"{\n\t\"logId\": \"623db263ce8355dce869d36f\",\n\t\"completed\": true\n}"},"parameters":[],"headers":[{"name":"Content-Type","value":"application/json","id":"pair_6257013847d3437db8aad41c78826168"}],"authentication":{"type":"bearer","token":"{{ _.TOKEN }}"},"metaSortKey":-1648201783348.5,"isPrivate":false,"settingStoreCookies":true,"settingSendCookies":true,"settingDisableRenderRequestBody":false,"settingEncodeUrl":true,"settingRebuildPath":true,"settingFollowRedirects":"global","_type":"request"},{"_id":"env_652b83b074372a90e2e33cc131ec0ee45294b223","parentId":"wrk_eee28770aef8475d9353d62399da17c3","modified":1652433812997,"created":1647179707838,"name":"Base Environment","data":{"URL":"http://localhost:5000","TOKEN":"eyJhbGciOiJIUzI1NiIsInR5cCI6IkpXVCJ9.eyJ1c2VySWQiOiI2MjU4MjQ1NTgxMTZjM2NkYzYxOTA4ZmEiLCJpYXQiOjE2NTI0MzM4MDEsImV4cCI6MTY1MzI5NzgwMX0.k9YbCEpbzs0qAIeo5vVSozrzvhqIDuc0R7Sv194tFlM"},"dataPropertyOrder":{"&":["URL","TOKEN"]},"color":null,"isPrivate":false,"metaSortKey":1647179707839,"_type":"environment"},{"_id":"jar_652b83b074372a90e2e33cc131ec0ee45294b223","parentId":"wrk_eee28770aef8475d9353d62399da17c3","modified":1647179707866,"created":1647179707866,"name":"Default Jar","cookies":[],"_type":"cookie_jar"},{"_id":"spc_5c381d0992194b0287d7059c4ab3bb94","parentId":"wrk_eee28770aef8475d9353d62399da17c3","modified":1652432921373,"created":1647179707828,"fileName":"New Document","contents":"","contentType":"yaml","_type":"api_spec"},{"_id":"uts_f5ca7a157f324a88871134e059a4dd18","parentId":"wrk_eee28770aef8475d9353d62399da17c3","modified":1647179707876,"created":1647179707876,"name":"Example Test Suite","_type":"unit_test_suite"},{"_id":"uts_78bbb2026e554059b275e41b97c7599d","parentId":"wrk_eee28770aef8475d9353d62399da17c3","modified":1647184750493,"created":1647184750493,"name":"workout-app","_type":"unit_test_suite"}]}